{
  "status": "success",
  "totalResults": 9,
  "articles": [
    {
      "title": "Official watch bands for your new Apple Watch are $34 off at Woot - The Verge",
      "source": {
        "name": "The Verge"
      },
      "description": "Woot has deeply discounted Apple Watch Solo Loop and Braided Loop bands. You can also save on a 128G...",
      "url": "https://www.theverge.com/tech/778766/apple-watch-solo-loop-band-ipad-air-m3-deal-sale",
      "publishedAt": "2025-09-16T15:30:00Z",
      "processed_at": "2025-09-17T20:21:26.728458+00:00"
    },
    {
      "title": "Xbox Game Pass Expands With 13 More Games In September - GameSpot",
      "source": {
        "name": "GameSpot"
      },
      "description": "Here's a closer look at everything being added to Game Pass this month....",
      "url": "https://www.gamespot.com/gallery/xbox-game-pass-expands-with-13-more-games-in-september/2900-7037/",
      "publishedAt": "2025-09-16T14:53:10Z",
      "processed_at": "2025-09-17T20:21:26.728458+00:00"
    },
    {
      "title": "Google Puts Its Popular AI Video Generator Into YouTube Shorts - The Wall Street Journal",
      "source": {
        "name": "The Wall Street Journal"
      },
      "description": "",
      "url": "https://www.wsj.com/tech/ai/youtube-shorts-veo-3-ai-video-03103dc7",
      "publishedAt": "2025-09-16T14:30:00Z",
      "processed_at": "2025-09-17T20:21:26.728458+00:00"
    },
    {
      "title": "iOS 26 Draining Your Battery? Apple Says It's Normal - CNET",
      "source": {
        "name": "CNET"
      },
      "description": "Some iPhones experience faster battery drain after an update, but Apple says this is temporary....",
      "url": "https://www.cnet.com/tech/services-and-software/ios-26-draining-your-battery-apple-says-its-normal/",
      "publishedAt": "2025-09-16T13:31:00Z",
      "processed_at": "2025-09-17T20:21:26.728458+00:00"
    },
    {
      "title": "Roku's first TV projector gives you a 150-inch screen - for less than $200 - ZDNET",
      "source": {
        "name": "ZDNet"
      },
      "description": "The Roku TV Smart Projector D1R Cube offers 1080p HD, 330 ANSI lumens, and dual 5W speakers, plus su...",
      "url": "https://www.zdnet.com/home-and-office/home-entertainment/rokus-first-tv-projector-gives-you-a-150-inch-screen-for-less-than-200/",
      "publishedAt": "2025-09-16T13:00:00Z",
      "processed_at": "2025-09-17T20:21:26.728458+00:00"
    },
    {
      "title": "Gearbox CEO Randy Pitchford tells Borderlands 4 critics to \"code your own engine,\" calls it a game for \"premium gamers\" - TechSpot",
      "source": {
        "name": "TechSpot"
      },
      "description": "While Borderlands 4 has received mostly positive reviews from critics, players have slammed the awfu...",
      "url": "https://www.techspot.com/news/109487-gearbox-ceo-randy-pitchford-tells-borderlands-4-critics.html",
      "publishedAt": "2025-09-16T12:03:00Z",
      "processed_at": "2025-09-17T20:21:26.728458+00:00"
    },
    {
      "title": "Meta’s new smart glasses are coming this week - The Verge",
      "source": {
        "name": "The Verge"
      },
      "description": "Mark Zuckerberg is set to keynote Meta Connect 2025 on Wednesday at 8PM ET, and we’re expecting to s...",
      "url": "https://www.theverge.com/news/777541/meta-connect-2025-what-to-expect",
      "publishedAt": "2025-09-16T12:00:00Z",
      "processed_at": "2025-09-17T20:21:26.728458+00:00"
    },
    {
      "title": "Hollow Knight: Silksong's second patch detailed, but don't expect any balance tweaks - Eurogamer",
      "source": {
        "name": "Eurogamer.net"
      },
      "description": "More fixes to bugs coming to Hollow Knight: Silksong, rather than any significant tweaks....",
      "url": "https://www.eurogamer.net/hollow-knight-silksongs-second-patch-detailed-but-dont-expect-any-balance-tweaks",
      "publishedAt": "2025-09-16T11:49:11Z",
      "processed_at": "2025-09-17T20:21:26.728458+00:00"
    },
    {
      "title": "One AirPods Pro 3 Feature Upgrade Comes With a Catch - MacRumors",
      "source": {
        "name": "MacRumors"
      },
      "description": "Apple's new AirPods Pro 3 boast a range of new features and improvements that make them a tempting u...",
      "url": "https://www.macrumors.com/2025/09/16/airpods-pro-3-feature-iphone-17/",
      "publishedAt": "2025-09-16T11:06:27Z",
      "processed_at": "2025-09-17T20:21:26.728458+00:00"
    }
  ],
  "lastUpdated": "2025-09-17T20:21:26.728521+00:00",
  "source": "NewsAPI",
  "metadata": {
    "processed_by": "GitHub Actions",
    "script_version": "2.0.0",
    "compatible_with": "scripts.js NewsManager"
  }
}