{
  "status": "success",
  "totalResults": 10,
  "articles": [
    {
      "title": "“Microslop”: Microsoft Stock (NASDAQ:MSFT) Gains Despite Growing Furor on Discord - TipRanks",
      "source": {
        "name": "Tipranks.com"
      },
      "description": "Tech giant Microsoft ($MSFT) spent a large portion of the last few days putting out fires in its Cop...",
      "url": "https://www.tipranks.com/news/microslop-microsoft-stock-nasdaqmsft-gains-despite-growing-furor-on-discord",
      "publishedAt": "2026-03-02T18:34:51Z",
      "processed_at": "2026-03-03T21:35:44.752363+00:00"
    },
    {
      "title": "Apple iPhone 18 Pro: New Leak Signals Unprecedented Design Change - Forbes",
      "source": {
        "name": "Forbes"
      },
      "description": "Exactly what the next iPhone will look like has become a little clearer thanks to a new report....",
      "url": "https://www.forbes.com/sites/davidphelan/2026/03/02/apple-iphone-18-pro-new-leak-signals-unprecedented-design-change/",
      "publishedAt": "2026-03-02T18:12:00Z",
      "processed_at": "2026-03-03T21:35:44.752363+00:00"
    },
    {
      "title": "/dev: MMR-to-Rank Distribution - League of Legends",
      "source": {
        "name": "Leagueoflegends.com"
      },
      "description": "Our goals for Ranked and some changes to keep your climbs fair and competitive....",
      "url": "https://www.leagueoflegends.com/en-us/news/dev/dev-mmr-to-rank-distribution/",
      "publishedAt": "2026-03-02T17:45:26Z",
      "processed_at": "2026-03-03T21:35:44.752363+00:00"
    },
    {
      "title": "Triceratops skeleton ‘Trey’ to hit the auction block as dinosaur market soars - AP News",
      "source": {
        "name": "Associated Press"
      },
      "description": "A triceratops skeleton that once greeted visitors at a Wyoming museum is heading to an online auctio...",
      "url": "https://apnews.com/article/dinosaur-fossil-auction-trey-triceratops-joopiter-437d0090e76287fd1409d5d8e9c01d5b",
      "publishedAt": "2026-03-02T17:18:00Z",
      "processed_at": "2026-03-03T21:35:44.752363+00:00"
    },
    {
      "title": "Resident Evil Requiem Final Puzzle solution - Eurogamer",
      "source": {
        "name": "Eurogamer.net"
      },
      "description": "How to solve the Final Puzzle and the 'Let the sweet pair hear the voice.' hint in Resident Evil Req...",
      "url": "https://www.eurogamer.net/resident-evil-requiem-final-puzzle",
      "publishedAt": "2026-03-02T16:28:09Z",
      "processed_at": "2026-03-03T21:35:44.752363+00:00"
    },
    {
      "title": "Return to New York - Magic: The Gathering",
      "source": {
        "name": "Wizards.com"
      },
      "description": "Learn how Magic brought turtle power to the Big Apple with Magic: The Gathering® | Teenage Mutant Ni...",
      "url": "https://magic.wizards.com/en/news/feature/return-to-new-york",
      "publishedAt": "2026-03-02T16:21:10Z",
      "processed_at": "2026-03-03T21:35:44.752363+00:00"
    },
    {
      "title": "Nintendo has set a new Indie World showcase of games coming to both Nintendo Switch 1 and 2, and it's happening very soon - Eurogamer",
      "source": {
        "name": "Eurogamer.net"
      },
      "description": "Nintendo has announced a new Indie World showcase will kick off March....",
      "url": "https://www.eurogamer.net/nintendo-indie-world-showcase-march-2026-announced",
      "publishedAt": "2026-03-02T16:17:14Z",
      "processed_at": "2026-03-03T21:35:44.752363+00:00"
    },
    {
      "title": "Pokemon FireRed and LeafGreen on Nintendo Switch fix massive glitch 22 years later - Nintendo Everything",
      "source": {
        "name": "Nintendoeverything.com"
      },
      "description": "An infamous roar glitch with Pokemon FireRed and LeafGreen have been fixed for Nintendo Switch - her...",
      "url": "https://nintendoeverything.com/pokemon-firered-leafgreen-switch-roar-bug-fixed/",
      "publishedAt": "2026-03-02T15:09:05Z",
      "processed_at": "2026-03-03T21:35:44.752363+00:00"
    },
    {
      "title": "Some Apple AI servers are reportedly sitting unused on warehouse shelves, due to low Apple Intelligence usage - 9to5Mac",
      "source": {
        "name": "9to5Mac"
      },
      "description": "Earlier this year, Bloomberg reported that Apple was looking to host the much-delayed new Siri model...",
      "url": "https://9to5mac.com/2026/03/02/some-apple-ai-servers-are-reportedly-sitting-unused-on-warehouse-shelves-due-to-low-apple-intelligence-usage/",
      "publishedAt": "2026-03-02T14:34:00Z",
      "processed_at": "2026-03-03T21:35:44.752363+00:00"
    },
    {
      "title": "Apple introduces iPhone 17e - Apple",
      "source": {
        "name": "Apple Newsroom"
      },
      "description": "Apple today announced the new iPhone 17e, a powerful and affordable addition to the iPhone 17 lineup...",
      "url": "https://www.apple.com/newsroom/2026/03/apple-introduces-iphone-17e/",
      "publishedAt": "2026-03-02T14:03:14Z",
      "processed_at": "2026-03-03T21:35:44.752363+00:00"
    }
  ],
  "lastUpdated": "2026-03-03T21:35:44.752471+00:00",
  "source": "NewsAPI",
  "metadata": {
    "processed_by": "GitHub Actions",
    "script_version": "2.0.0",
    "compatible_with": "scripts.js NewsManager"
  }
}