{
  "status": "success",
  "totalResults": 8,
  "articles": [
    {
      "title": "Ninja Gaiden 4 is the perfect place to jump into the series - The Verge",
      "source": {
        "name": "The Verge"
      },
      "description": "Ninja Gaiden 4 has action-packed fights and a ridiculous new protagonist. The game will be available...",
      "url": "https://www.theverge.com/games/802755/ninja-gaiden-4-review-xbox-series-x-s-ps5-pc",
      "publishedAt": "2025-10-20T23:00:00Z",
      "processed_at": "2025-10-22T07:20:01.330168+00:00"
    },
    {
      "title": "Snapchat is down — live updates on AWS outage and its impact on the social media app - Tom's Guide",
      "source": {
        "name": "Tom's Guide"
      },
      "description": "Snapchat has stopped working for a lot of users...",
      "url": "https://www.tomsguide.com/news/live/snapchat-outage-live-october-20",
      "publishedAt": "2025-10-20T22:32:56Z",
      "processed_at": "2025-10-22T07:20:01.330168+00:00"
    },
    {
      "title": "Apple will let users roll back the Liquid Glass look with new ‘tinted’ option - TechCrunch",
      "source": {
        "name": "TechCrunch"
      },
      "description": "Apple is responding to user feedback on its new Liquid Glass design with a setting that lets users c...",
      "url": "https://techcrunch.com/2025/10/20/apple-will-let-users-roll-back-the-liquid-glass-look-with-new-tinted-option/",
      "publishedAt": "2025-10-20T21:40:41Z",
      "processed_at": "2025-10-22T07:20:01.330168+00:00"
    },
    {
      "title": "Apple Watch Ultra 3 after one month: The feature I can’t give up - 9to5Mac",
      "source": {
        "name": "9to5Mac"
      },
      "description": "Apple Watch Ultra 3 after one month: Here’s what my experience has been like as someone new to the U...",
      "url": "https://9to5mac.com/2025/10/20/apple-watch-ultra-3-after-one-month-feature-cant-give-up/",
      "publishedAt": "2025-10-20T20:57:00Z",
      "processed_at": "2025-10-22T07:20:01.330168+00:00"
    },
    {
      "title": "Duffy says NASA will open Artemis 3 lander contract to competition - SpaceNews",
      "source": {
        "name": "SpaceNews"
      },
      "description": "",
      "url": "https://spacenews.com/duffy-says-nasa-will-open-artemis-3-lander-contract-to-competition/",
      "publishedAt": "2025-10-20T20:50:04Z",
      "processed_at": "2025-10-22T07:20:01.330168+00:00"
    },
    {
      "title": "Google reportedly searching for 15 Pixel “Superfans” to test unreleased phones - Ars Technica",
      "source": {
        "name": "Ars Technica"
      },
      "description": "Selected testers will have to sign an NDA and use a disguised case....",
      "url": "https://arstechnica.com/gadgets/2025/10/google-reportedly-searching-for-15-pixel-superfans-to-test-unreleased-phones/",
      "publishedAt": "2025-10-20T20:14:29Z",
      "processed_at": "2025-10-22T07:20:01.330168+00:00"
    },
    {
      "title": "Take Your Apple Watch Experience to the Next Level With These 8 Tips and Tricks - CNET",
      "source": {
        "name": "CNET"
      },
      "description": "Get the most out of your Apple Watch with these expert-approved tips....",
      "url": "https://www.cnet.com/tech/mobile/take-your-apple-watch-experience-to-the-next-level-with-these-8-tips-and-tricks/",
      "publishedAt": "2025-10-20T19:45:00Z",
      "processed_at": "2025-10-22T07:20:01.330168+00:00"
    },
    {
      "title": "IgNobel 'Butt Breathing' idea from 2024 moves closer to real treatment - Medical Xpress",
      "source": {
        "name": "Medical Xpress"
      },
      "description": "The technique sounds so outlandish that it won an IgNobel prize in 2024. But the science behind resc...",
      "url": "https://medicalxpress.com/news/2025-10-ignobel-butt-idea-closer-real.html",
      "publishedAt": "2025-10-20T19:19:35Z",
      "processed_at": "2025-10-22T07:20:01.330168+00:00"
    }
  ],
  "lastUpdated": "2025-10-22T07:20:01.330237+00:00",
  "source": "NewsAPI",
  "metadata": {
    "processed_by": "GitHub Actions",
    "script_version": "2.0.0",
    "compatible_with": "scripts.js NewsManager"
  }
}