{
  "status": "success",
  "totalResults": 8,
  "articles": [
    {
      "title": "Apple’s ‘Veritas’ chatbot is reportedly an employee-only test of Siri’s AI upgrades - The Verge",
      "source": {
        "name": "The Verge"
      },
      "description": "There’s no plans for a public release of Apple’s internal Veritas chatbot and will likely lean on Go...",
      "url": "https://www.theverge.com/news/787046/apples-veritas-siri-ai-chatbot",
      "publishedAt": "2025-09-28T21:01:41Z",
      "processed_at": "2025-09-30T01:27:27.468311+00:00"
    },
    {
      "title": "These Are The Rarest Ford Vehicles You've Probably Never Heard Of - Jalopnik",
      "source": {
        "name": "Jalopnik"
      },
      "description": "Some of the rarest Fords ever built include models like the Fairlane 500 R-Code, Mustang V10, Mustan...",
      "url": "https://www.jalopnik.com/1976913/rarest-ford-vehicles-never-heard-of/",
      "publishedAt": "2025-09-28T20:05:00Z",
      "processed_at": "2025-09-30T01:27:27.468311+00:00"
    },
    {
      "title": "Google Pixel 10 vs. Pixel 10 Pro - GSMArena.com",
      "source": {
        "name": "GSMArena.com"
      },
      "description": "Which small Pixel is the right fit for you? For another year, Google's hardware department is outing...",
      "url": "https://www.gsmarena.com/google_pixel_10_vs_pixel_10_pro_review_battery_camera_price_compared-news-69594.php",
      "publishedAt": "2025-09-28T20:04:01Z",
      "processed_at": "2025-09-30T01:27:27.468311+00:00"
    },
    {
      "title": "Parasite Eve-Inspired Sci-fi Horror RPG Parasite Mutant Revealed for PC and PS5 - Final Weapon",
      "source": {
        "name": "Finalweapon.net"
      },
      "description": "IceSitruuna, the developer behind Frontier Hunter: Erza's Wheel of Fortune, reveals Parasite Eve-ins...",
      "url": "https://finalweapon.net/2025/09/28/parasite-eve-inspired-sci-fi-horror-rpg-parasite-mutant-pc-ps5/",
      "publishedAt": "2025-09-28T19:14:52Z",
      "processed_at": "2025-09-30T01:27:27.468311+00:00"
    },
    {
      "title": "Here’s how Apple Stores are combating iPhone 17 scratches - 9to5Mac",
      "source": {
        "name": "9to5Mac"
      },
      "description": "Apple Stores are taking two important steps to try and prevent scratches and marks on their display ...",
      "url": "https://9to5mac.com/2025/09/28/heres-how-apple-stores-are-combating-iphone-17-scratches/",
      "publishedAt": "2025-09-28T18:47:00Z",
      "processed_at": "2025-09-30T01:27:27.468311+00:00"
    },
    {
      "title": "Persona 3 Reload director discusses the \"graphics quality\" of the Switch 2 version - GoNintendo",
      "source": {
        "name": "GoNintendo"
      },
      "description": "Does Reload need a revamp?...",
      "url": "https://gonintendo.com/contents/53374-persona-3-reload-director-discusses-the-graphics-quality-of-the-switch-2-version",
      "publishedAt": "2025-09-28T18:17:09Z",
      "processed_at": "2025-09-30T01:27:27.468311+00:00"
    },
    {
      "title": "Pokémon GO Events This Week (29 September – 5 October 2025) - Pokémon GO Hub",
      "source": {
        "name": "Pokemon GO Hub"
      },
      "description": "Pokémon GO’s September 29 to October 5 schedule brings to a close the first month in of the Tales of...",
      "url": "https://pokemongohub.net/post/event/pokemon-go-events-this-week-29-september-5-october-2025/",
      "publishedAt": "2025-09-28T18:16:35Z",
      "processed_at": "2025-09-30T01:27:27.468311+00:00"
    },
    {
      "title": "This Week’s Japanese Game Releases: Ghost of Yotei, Digimon Story: Time Stranger, Final Fantasy Tactics: The Ivalice Chronicles, more - Gematsu",
      "source": {
        "name": "Gematsu"
      },
      "description": "Ghost of Yotei for PlayStation 5, Digimon Story: Time Stranger for PlayStation 5, Xbox Series, and P...",
      "url": "https://www.gematsu.com/2025/09/this-weeks-japanese-game-releases-ghost-of-yotei-digimon-story-time-stranger-final-fantasy-tactics-the-ivalice-chronicles-more",
      "publishedAt": "2025-09-28T17:45:10Z",
      "processed_at": "2025-09-30T01:27:27.468311+00:00"
    }
  ],
  "lastUpdated": "2025-09-30T01:27:27.468382+00:00",
  "source": "NewsAPI",
  "metadata": {
    "processed_by": "GitHub Actions",
    "script_version": "2.0.0",
    "compatible_with": "scripts.js NewsManager"
  }
}