{
  "status": "success",
  "totalResults": 10,
  "articles": [
    {
      "title": "Give Your Phone a Huge (and Free) Upgrade by Switching to Another Keyboard - WIRED",
      "source": {
        "name": "Wired"
      },
      "description": "",
      "url": "https://www.wired.com/story/switch-your-phone-to-another-keyboard-ios-android/",
      "publishedAt": "2026-03-22T10:30:00Z",
      "processed_at": "2026-03-23T13:12:12.038963+00:00"
    },
    {
      "title": "Multiple Switch Games Receive Switch 2 Compatibility Fixes - Nintendo Life",
      "source": {
        "name": "Nintendo Life"
      },
      "description": "Kirby, Final Fantasy and more...",
      "url": "https://www.nintendolife.com/news/2026/03/multiple-switch-games-receive-switch-2-compatibility-fixes",
      "publishedAt": "2026-03-22T04:35:00Z",
      "processed_at": "2026-03-23T13:12:12.038963+00:00"
    },
    {
      "title": "Bloodstained: The Scarlet Engagement listed for Nintendo Switch, plus an unannounced 505 Games Switch 2 title - Nintendo Everything",
      "source": {
        "name": "Nintendoeverything.com"
      },
      "description": "Bloodstained: The Scarlet Engagement has been listed for Nintendo Switch alongside an unannounced Sw...",
      "url": "https://nintendoeverything.com/bloodstained-the-scarlet-engagement-listed-for-nintendo-switch-plus-an-unannounced-505-games-switch-2-title/",
      "publishedAt": "2026-03-22T04:04:50Z",
      "processed_at": "2026-03-23T13:12:12.038963+00:00"
    },
    {
      "title": "Deals: Galaxy S26 series gets its first price drop, the Pixel 10 series drops even further - GSMArena.com news - GSMArena.com",
      "source": {
        "name": "GSMArena.com"
      },
      "description": "Meanwhile, the 2025 MacBook Airs are getting cheaper too - not quite as cheap as the Neo, but they a...",
      "url": "https://www.gsmarena.com/deals_galaxy_s26_series_gets_its_first_price_drop_the_pixel_10_series_drops_even_further-news-72031.php",
      "publishedAt": "2026-03-22T01:31:02Z",
      "processed_at": "2026-03-23T13:12:12.038963+00:00"
    },
    {
      "title": "5 Rammed Earth Homes in 2026 That Make Concrete Walls Look Outdated - Yanko Design",
      "source": {
        "name": "Yanko Design"
      },
      "description": "The architectural world is shifting toward materials that feel grounded, honest, and deeply connecte...",
      "url": "https://www.yankodesign.com/2026/03/21/5-rammed-earth-homes-in-2026-that-make-concrete-walls-look-outdated/",
      "publishedAt": "2026-03-21T23:30:29Z",
      "processed_at": "2026-03-23T13:12:12.038963+00:00"
    },
    {
      "title": "These 18+ New PS5, PS4 Games Are Coming Out Next Week (23rd-29th March) - Push Square",
      "source": {
        "name": "Push Square"
      },
      "description": "Life Is Strange! Screamer! Mega Man!...",
      "url": "https://www.pushsquare.com/guides/these-18plus-new-ps5-ps4-games-are-coming-out-next-week-23rd-29th-march",
      "publishedAt": "2026-03-21T23:06:09Z",
      "processed_at": "2026-03-23T13:12:12.038963+00:00"
    },
    {
      "title": "PSN Service Returning on PS5, PS4 as Brief Outage Took Service Offline - Push Square",
      "source": {
        "name": "Push Square"
      },
      "description": "Taken offline for roughly two hours...",
      "url": "https://www.pushsquare.com/news/2026/03/psn-service-returning-on-ps5-ps4-as-brief-outage-took-service-offline",
      "publishedAt": "2026-03-21T22:45:00Z",
      "processed_at": "2026-03-23T13:12:12.038963+00:00"
    },
    {
      "title": "4 Features The C9 Corvette Needs To Put Itself Ahead Of The Pack - SlashGear",
      "source": {
        "name": "SlashGear"
      },
      "description": "Chevrolet launched the Corvette into the supercar stratosphere with the C8. Now the C9 faces a lofty...",
      "url": "https://www.slashgear.com/2125157/chevrolet-corvette-features-specs-wishlist/",
      "publishedAt": "2026-03-21T22:30:00Z",
      "processed_at": "2026-03-23T13:12:12.038963+00:00"
    },
    {
      "title": "New Xbox First-Party Game Announced In The Form Of Minecraft Dungeons 2 - Pure Xbox",
      "source": {
        "name": "Pure Xbox"
      },
      "description": "\"Return to the world in an all new action RPG adventure\"...",
      "url": "https://www.purexbox.com/news/2026/03/new-xbox-first-party-game-announced-in-the-form-of-minecraft-dungeons-2",
      "publishedAt": "2026-03-21T21:48:51Z",
      "processed_at": "2026-03-23T13:12:12.038963+00:00"
    },
    {
      "title": "Does anyone even use 3-button navigation anymore? - Android Central",
      "source": {
        "name": "Android Central"
      },
      "description": "How many of you are still using 3-button navigation on your Android phones?...",
      "url": "https://www.androidcentral.com/apps-software/poll-does-anyone-even-use-3-button-navigation-anymore",
      "publishedAt": "2026-03-21T21:21:56Z",
      "processed_at": "2026-03-23T13:12:12.038963+00:00"
    }
  ],
  "lastUpdated": "2026-03-23T13:12:12.039031+00:00",
  "source": "NewsAPI",
  "metadata": {
    "processed_by": "GitHub Actions",
    "script_version": "2.0.0",
    "compatible_with": "scripts.js NewsManager"
  }
}