{
  "status": "success",
  "totalResults": 8,
  "articles": [
    {
      "title": "iOS 27’s new Siri design will look like this, per report - 9to5Mac",
      "source": {
        "name": "9to5Mac"
      },
      "description": "Apple’s major Siri overhaul will be unveiled soon, and a new report reveals exactly what to expect f...",
      "url": "https://9to5mac.com/2026/05/26/ios-27s-new-siri-design-will-look-like-this-per-report/",
      "publishedAt": "2026-05-26T15:51:00Z",
      "processed_at": "2026-05-27T16:38:27.307444+00:00"
    },
    {
      "title": "Most Valuable Cards from \"Abyss Eye,\" Slowbro the Favorite Illustration Rare! - PokeBeach",
      "source": {
        "name": "Pokebeach.com"
      },
      "description": "Abyss Eye released in Japan on Friday! I've gathered card prices from online stores to give us a clu...",
      "url": "https://www.pokebeach.com/?p=320704",
      "publishedAt": "2026-05-26T15:01:10Z",
      "processed_at": "2026-05-27T16:38:27.307444+00:00"
    },
    {
      "title": "Nvidia has retired its GeForce Control Panel app after 20 years - The Verge",
      "source": {
        "name": "The Verge"
      },
      "description": "Nvidia has now ported across all of the major Control Panel features to its Nvidia app....",
      "url": "https://www.theverge.com/news/937221/nvidia-geforce-control-panel-app-retirement",
      "publishedAt": "2026-05-26T14:14:35Z",
      "processed_at": "2026-05-27T16:38:27.307444+00:00"
    },
    {
      "title": "iPhone 18 Pro Max vs Google Pixel 11 Pro XL: Main differences to expect - PhoneArena",
      "source": {
        "name": "PhoneArena"
      },
      "description": "",
      "url": "https://www.phonearena.com/reviews/apple-iphone-18-pro-max-vs-google-pixel-11-pro-xl_id7937",
      "publishedAt": "2026-05-26T14:02:52Z",
      "processed_at": "2026-05-27T16:38:27.307444+00:00"
    },
    {
      "title": "Hundreds of Marvel Rivals cheats named and shamed in \"an immediate, targeted purge\" - Eurogamer",
      "source": {
        "name": "Eurogamer.net"
      },
      "description": "Played against someone in Marvel Rivals you think is cheating? Their name might be on this list....",
      "url": "https://www.eurogamer.net/marvel-rivals-exploiters-cheats-named-shamed",
      "publishedAt": "2026-05-26T13:08:33Z",
      "processed_at": "2026-05-27T16:38:27.307444+00:00"
    },
    {
      "title": "Here are our PS Plus monthly games for June, with an Xbox title headlining - Eurogamer",
      "source": {
        "name": "Eurogamer.net"
      },
      "description": "Sony has announced its PlayStation Plus games for June....",
      "url": "https://www.eurogamer.net/here-are-our-ps-plus-monthly-games-for-june-with-an-xbox-title-headlining",
      "publishedAt": "2026-05-26T12:56:18Z",
      "processed_at": "2026-05-27T16:38:27.307444+00:00"
    },
    {
      "title": "Nobody wants to tell me why they only listen to their own Suno slop - The Verge",
      "source": {
        "name": "The Verge"
      },
      "description": "Suno users are abandoning Spotify, and real music for their own AI slop....",
      "url": "https://www.theverge.com/ai-artificial-intelligence/937059/nobody-wants-to-tell-me-why-they-only-listen-their-own-suno-slop",
      "publishedAt": "2026-05-26T12:46:03Z",
      "processed_at": "2026-05-27T16:38:27.307444+00:00"
    },
    {
      "title": "4 new pizzerias up the ante for neighborhood joints - Pittsburgh Post-Gazette",
      "source": {
        "name": "Pittsburgh Post-Gazette"
      },
      "description": "False...",
      "url": "https://www.post-gazette.com/life/dining/2026/05/26/pittsburgh-pizza-news-paps-muns-slice-squared-burghers/stories/202605220046",
      "publishedAt": "2026-05-26T12:32:25Z",
      "processed_at": "2026-05-27T16:38:27.307444+00:00"
    }
  ],
  "lastUpdated": "2026-05-27T16:38:27.307510+00:00",
  "source": "NewsAPI",
  "metadata": {
    "processed_by": "GitHub Actions",
    "script_version": "2.0.0",
    "compatible_with": "scripts.js NewsManager"
  }
}