{
  "status": "success",
  "totalResults": 10,
  "articles": [
    {
      "title": "Top Stories: Major Apple Devices Leak, $599 MacBook Rumor, and More - MacRumors",
      "source": {
        "name": "MacRumors"
      },
      "description": "Apple this week briefly made a file available that contained identifiers for many unreleased devices...",
      "url": "https://www.macrumors.com/2025/08/16/top-stories-apple-devices-leak-and-more/",
      "publishedAt": "2025-08-16T23:15:00Z",
      "processed_at": "2025-08-18T06:35:26.043069+00:00"
    },
    {
      "title": "Ubisoft seemingly bulked out Assassin’s Creed games to delay people reselling - My Nintendo News",
      "source": {
        "name": "My Nintendo News"
      },
      "description": "Assassin’s Creed is a long-running franchise which still generates lots of sales with the latest gam...",
      "url": "https://mynintendonews.com/2025/08/16/ubisoft-seemingly-bulked-out-assassins-creed-games-to-delay-people-reselling/",
      "publishedAt": "2025-08-16T22:09:53Z",
      "processed_at": "2025-08-18T06:35:26.043069+00:00"
    },
    {
      "title": "I Used an AI-Powered Glucose Monitor for 2 Weeks. Here's What Surprised Me - CNET",
      "source": {
        "name": "CNET"
      },
      "description": "I paired my Oura ring with Dexcom's Stelo AI-powered CGM and learned three key things about my eatin...",
      "url": "https://www.cnet.com/health/medical/i-used-an-ai-powered-glucose-monitor-for-2-weeks-heres-what-surprised-me/",
      "publishedAt": "2025-08-16T22:03:00Z",
      "processed_at": "2025-08-18T06:35:26.043069+00:00"
    },
    {
      "title": "Support for Ninjala appears to be over - Nintendo Everything",
      "source": {
        "name": "Nintendoeverything.com"
      },
      "description": "Ninjala gets patch notes for Season 21, and it looks like support for the game is wrapping up with t...",
      "url": "https://nintendoeverything.com/ninjala-support-ends/",
      "publishedAt": "2025-08-16T21:31:57Z",
      "processed_at": "2025-08-18T06:35:26.043069+00:00"
    },
    {
      "title": "2026 BMW M850i Edition M Heritage Is BMW's Very Red Farewell To The 8 Series - Jalopnik",
      "source": {
        "name": "Jalopnik"
      },
      "description": "Only 500 will ever be built, so if you want one, you'd better hurry up and place your order....",
      "url": "https://www.jalopnik.com/1941218/2026-bmw-m850i-m-heritage-reveal/",
      "publishedAt": "2025-08-16T21:05:00Z",
      "processed_at": "2025-08-18T06:35:26.043069+00:00"
    },
    {
      "title": "Dragon Ball Sparking Zero details Nintendo Switch 2 and Switch frame rate and resolution, official comparison - Nintendo Everything",
      "source": {
        "name": "Nintendoeverything.com"
      },
      "description": "Dragon Ball Sparking Zero for Nintendo Switch 2 and Switch get details on frame rate and resolution,...",
      "url": "https://nintendoeverything.com/dragon-ball-sparking-zero-details-nintendo-switch-2-and-switch-frame-rate-and-resolution-official-comparison/",
      "publishedAt": "2025-08-16T20:15:32Z",
      "processed_at": "2025-08-18T06:35:26.043069+00:00"
    },
    {
      "title": "AI-powered stuffed animals are coming for your kids - TechCrunch",
      "source": {
        "name": "TechCrunch"
      },
      "description": "Do A.I. chatbots packaged inside cute-looking plushies offer a viable alternative to screen time for...",
      "url": "https://techcrunch.com/2025/08/16/ai-powered-stuffed-animals-are-coming-for-your-kids/",
      "publishedAt": "2025-08-16T19:39:40Z",
      "processed_at": "2025-08-18T06:35:26.043069+00:00"
    },
    {
      "title": "DSLR vs Mirrorless Cameras: Why My DSLR Still Wins - PetaPixel",
      "source": {
        "name": "PetaPixel"
      },
      "description": "Professional photographer Bimal Nepal shares why he still favors his DSLR camera for his work in the...",
      "url": "https://petapixel.com/2025/08/16/dslr-vs-mirrorless-cameras-why-my-dslr-still-wins/",
      "publishedAt": "2025-08-16T18:00:37Z",
      "processed_at": "2025-08-18T06:35:26.043069+00:00"
    },
    {
      "title": "5 smart display tricks that quietly changed how I live - Android Police",
      "source": {
        "name": "Android Police"
      },
      "description": "These smart display features proved surprisingly useful after I tried them...",
      "url": "https://www.androidpolice.com/smart-display-tricks-changed-how-i-live/",
      "publishedAt": "2025-08-16T17:42:00Z",
      "processed_at": "2025-08-18T06:35:26.043069+00:00"
    },
    {
      "title": "Meet the 'neglectons': Previously overlooked particles that could revolutionize quantum computing - Live Science",
      "source": {
        "name": "Live Science"
      },
      "description": "When mathematicians revived ignored mathematical structures, they found that overlooked particles, c...",
      "url": "https://www.livescience.com/physics-mathematics/meet-the-neglectons-previously-overlooked-particles-that-could-revolutionize-quantum-computing",
      "publishedAt": "2025-08-16T17:12:00Z",
      "processed_at": "2025-08-18T06:35:26.043069+00:00"
    }
  ],
  "lastUpdated": "2025-08-18T06:35:26.043140+00:00",
  "source": "NewsAPI",
  "metadata": {
    "processed_by": "GitHub Actions",
    "script_version": "2.0.0",
    "compatible_with": "scripts.js NewsManager"
  }
}