{
  "status": "success",
  "totalResults": 10,
  "articles": [
    {
      "title": "‘Flow’ dramatically improves Android voice typing without replacing Gboard - 9to5Google",
      "source": {
        "name": "9to5google.com"
      },
      "description": "Voice-to-text on Android is really good if you’re using a Pixel, and pretty hit or miss everywhere e...",
      "url": "http://9to5google.com/2026/02/23/flow-dramatically-improves-android-voice-typing-without-replacing-gboard/",
      "publishedAt": "2026-02-23T08:01:00Z",
      "processed_at": "2026-02-24T11:41:37.535886+00:00"
    },
    {
      "title": "Sony Goes Silent on Social Media for Over 72 Hours as Fans Turn Feral Following Bluepoint Closure - Push Square",
      "source": {
        "name": "Push Square"
      },
      "description": "Gloves off...",
      "url": "https://www.pushsquare.com/news/2026/02/sony-goes-silent-on-social-media-for-over-72-hours-as-fans-turn-feral-following-bluepoint-closure",
      "publishedAt": "2026-02-23T05:39:05Z",
      "processed_at": "2026-02-24T11:41:37.535886+00:00"
    },
    {
      "title": "Forget a Second Screen, This $799 Portable Monitor Adds Three 18.5-Inch Displays to Your Laptop - Yanko Design",
      "source": {
        "name": "Yanko Design"
      },
      "description": "The average laptop screen sits somewhere between 13 and 15.6 inches, which sounds perfectly reasonab...",
      "url": "https://www.yankodesign.com/2026/02/22/forget-a-second-screen-this-799-portable-monitor-adds-three-18-5-inch-displays-to-your-laptop/",
      "publishedAt": "2026-02-23T02:45:24Z",
      "processed_at": "2026-02-24T11:41:37.535886+00:00"
    },
    {
      "title": "4 Things You Didn't Know HDMI Ports Can Do - SlashGear",
      "source": {
        "name": "SlashGear"
      },
      "description": "HDMI ports can unlock enhanced video modes, auto game mode switching, 4K at 120Hz with VRR, and high...",
      "url": "https://www.slashgear.com/2104457/things-you-didnt-know-hdmi-ports-can-do/",
      "publishedAt": "2026-02-23T02:45:00Z",
      "processed_at": "2026-02-24T11:41:37.535886+00:00"
    },
    {
      "title": "The FBI Says These Wi-Fi Routers Are Unsafe, And Here's Why - SlashGear",
      "source": {
        "name": "SlashGear"
      },
      "description": "The FBI has named a series of Wi-Fi routers as being unsafe. If you're using a router from this bran...",
      "url": "https://www.slashgear.com/2104404/wifi-routers-unsafe-fbi-warning/",
      "publishedAt": "2026-02-23T01:45:00Z",
      "processed_at": "2026-02-24T11:41:37.535886+00:00"
    },
    {
      "title": "iOS 26.3.1 Update for iPhones Coming Soon as 'Apple Experience' Nears - MacRumors",
      "source": {
        "name": "MacRumors"
      },
      "description": "Apple's software engineers are testing iOS 26.3.1, according to the MacRumors visitor logs, which ha...",
      "url": "https://www.macrumors.com/2026/02/22/ios-26-3-1-coming-soon/",
      "publishedAt": "2026-02-23T01:29:51Z",
      "processed_at": "2026-02-24T11:41:37.535886+00:00"
    },
    {
      "title": "Linus Torvalds jokingly ponders his successor as Linux boss - theregister.com",
      "source": {
        "name": "Theregister.com"
      },
      "description": ": Emperor Penguin releases kernel 7.0 rc1 with some numerological musings...",
      "url": "https://www.theregister.com/2026/02/23/linux_7_0_rc1/",
      "publishedAt": "2026-02-23T00:56:00Z",
      "processed_at": "2026-02-24T11:41:37.535886+00:00"
    },
    {
      "title": "This is why you should stop connecting your Smart TV to WiFi and what you should do instead - supercarblondie.com",
      "source": {
        "name": "Supercarblondie.com"
      },
      "description": "If your Smart TV struggles to stream flawlessly, it could be because your WiFi signal isn’t quite up...",
      "url": "https://supercarblondie.com/tech/stop-connecting-smart-tv-wifi/",
      "publishedAt": "2026-02-23T00:48:00Z",
      "processed_at": "2026-02-24T11:41:37.535886+00:00"
    },
    {
      "title": "Jay Leno Owns The Katharine Hepburn Bugatti And That's Not Even The Interesting Part - Jalopnik",
      "source": {
        "name": "Jalopnik"
      },
      "description": "Jay Leno's Bugatti T38A starred in 'Christopher Strong' with Katherine Hepburn and several other fil...",
      "url": "https://www.jalopnik.com/2105042/jay-leno-katharine-hepburn-bugatti/",
      "publishedAt": "2026-02-23T00:05:00Z",
      "processed_at": "2026-02-24T11:41:37.535886+00:00"
    },
    {
      "title": "Google restricting Google AI Pro/Ultra subscribers for using OpenClaw - Hacker News",
      "source": {
        "name": "Hacker News"
      },
      "description": "",
      "url": "https://news.ycombinator.com/item?id\\\\u003d47115805",
      "publishedAt": "2026-02-22T23:48:12Z",
      "processed_at": "2026-02-24T11:41:37.535886+00:00"
    }
  ],
  "lastUpdated": "2026-02-24T11:41:37.535960+00:00",
  "source": "NewsAPI",
  "metadata": {
    "processed_by": "GitHub Actions",
    "script_version": "2.0.0",
    "compatible_with": "scripts.js NewsManager"
  }
}