{
  "status": "success",
  "totalResults": 10,
  "articles": [
    {
      "title": "Here are three reasons you shouldn’t quite consider Apple Watch Series 11 - 9to5Mac",
      "source": {
        "name": "9to5Mac"
      },
      "description": "Apple’s latest generation Apple Watch model, the Series 11, was just unveiled on Tuesday. While at f...",
      "url": "https://9to5mac.com/2025/09/13/apple-watch-series-11-why-you-shouldnt-necessarily-buy/",
      "publishedAt": "2025-09-13T15:53:00Z",
      "processed_at": "2025-09-14T18:24:35.076373+00:00"
    },
    {
      "title": "Spotify Lossless is an inconvenient improvement - The Verge",
      "source": {
        "name": "The Verge"
      },
      "description": "Spotify Lossless is clearly better than a normal stream, but improvements over “high quality” audio ...",
      "url": "https://www.theverge.com/hands-on/777691/spotify-lossless-flac-audio-inconvenient-improvement",
      "publishedAt": "2025-09-13T15:00:00Z",
      "processed_at": "2025-09-14T18:24:35.076373+00:00"
    },
    {
      "title": "AirPods Pro 3 will be available in under a week, but don’t rush into buying them - 9to5Mac",
      "source": {
        "name": "9to5Mac"
      },
      "description": "On Tuesday, Apple held its ‘Awe dropping’ September event – where it announced new iPhone and Apple ...",
      "url": "https://9to5mac.com/2025/09/13/heres-why-you-should-wait-to-buy-apple-airpods-pro-3/",
      "publishedAt": "2025-09-13T13:50:00Z",
      "processed_at": "2025-09-14T18:24:35.076373+00:00"
    },
    {
      "title": "Exclusive: Google wants to make Android phones safer by switching to ‘risk-based’ security updates - Android Authority",
      "source": {
        "name": "Android Authority"
      },
      "description": "Google’s new ‘risk-based’ approach to Android security updates prioritizes high-risk security issues...",
      "url": "https://www.androidauthority.com/android-risk-based-security-updates-3597466/",
      "publishedAt": "2025-09-13T11:42:16Z",
      "processed_at": "2025-09-14T18:24:35.076373+00:00"
    },
    {
      "title": "Did Apple ‘downgrade’ the telephoto camera with the iPhone 17 Pro? Here’s what you need to know - Tom's Guide",
      "source": {
        "name": "Tom's Guide"
      },
      "description": "It's more than just a simple 'crop'...",
      "url": "https://www.tomsguide.com/phones/iphones/did-apple-downgrade-the-telephoto-camera-with-the-iphone-17-pro-heres-what-you-need-to-know",
      "publishedAt": "2025-09-13T10:01:00Z",
      "processed_at": "2025-09-14T18:24:35.076373+00:00"
    },
    {
      "title": "Tips on stepping back from screens and starting a new hobby - AP News",
      "source": {
        "name": "Associated Press"
      },
      "description": "A lot of us want to reduce our time spent on screens. Experts say picking up a new hobby can help do...",
      "url": "https://apnews.com/article/finding-a-hobby-screen-alternatives-ef4c9320e1ede4a0b3ce04f5f4b149dd",
      "publishedAt": "2025-09-13T06:51:00Z",
      "processed_at": "2025-09-14T18:24:35.076373+00:00"
    },
    {
      "title": "Staffordshire Super Mario fan with major merchandise collection - BBC",
      "source": {
        "name": "BBC News"
      },
      "description": "As the iconic video game character turns 40, meet the fan who has amassed a major Mario collection....",
      "url": "https://www.bbc.com/news/articles/cj6x5574enpo",
      "publishedAt": "2025-09-13T06:26:25Z",
      "processed_at": "2025-09-14T18:24:35.076373+00:00"
    },
    {
      "title": "Strong appetite for new iPhone in China as pre-orders break record - South China Morning Post",
      "source": {
        "name": "Post Magazine"
      },
      "description": "The numbers underscore Apple’s brand loyalty in China despite growing competition from the likes of ...",
      "url": "https://www.scmp.com/tech/big-tech/article/3325424/chinese-pre-orders-apples-iphone-17-break-records-amid-strong-demand",
      "publishedAt": "2025-09-13T06:00:47Z",
      "processed_at": "2025-09-14T18:24:35.076373+00:00"
    },
    {
      "title": "Metroid Prime 4 Game And Samus Amiibo Preorders Available Now - GameSpot",
      "source": {
        "name": "GameSpot"
      },
      "description": "Metroid Prime 4: Beyond launches December 4 on Switch and Switch 2, and fans can also preorder three...",
      "url": "https://www.gamespot.com/articles/metroid-prime-4-beyond-game-amiibo-preorder-buying-guide-nintendo-switch-2/1100-6530754/",
      "publishedAt": "2025-09-13T05:12:18Z",
      "processed_at": "2025-09-14T18:24:35.076373+00:00"
    },
    {
      "title": "New Kirby amiibo Will Apparently Be Nintendo's \"Most Expensive amiibo Ever\" - Nintendo Life",
      "source": {
        "name": "Nintendo Life"
      },
      "description": "Suck it up...",
      "url": "https://www.nintendolife.com/news/2025/09/new-kirby-amiibo-will-apparently-be-nintendos-most-expensive-amiibo-ever",
      "publishedAt": "2025-09-13T03:55:00Z",
      "processed_at": "2025-09-14T18:24:35.076373+00:00"
    }
  ],
  "lastUpdated": "2025-09-14T18:24:35.076455+00:00",
  "source": "NewsAPI",
  "metadata": {
    "processed_by": "GitHub Actions",
    "script_version": "2.0.0",
    "compatible_with": "scripts.js NewsManager"
  }
}