{
  "status": "success",
  "totalResults": 10,
  "articles": [
    {
      "title": "The New Roku Update Is Terrible And Everyone Hates It - Kotaku",
      "source": {
        "name": "Kotaku"
      },
      "description": "Stop fucking things up just to shove more ads and algorithm nonsense into my face...",
      "url": "https://kotaku.com/its-not-just-you-everyone-is-mad-at-rokus-horrible-update-2000714762",
      "publishedAt": "2026-07-10T20:48:34Z",
      "processed_at": "2026-07-11T23:56:01.341431+00:00"
    },
    {
      "title": "God Of War Laufey Promises PS5 Disc, Teasing 2027 Release Date - Kotaku",
      "source": {
        "name": "Kotaku"
      },
      "description": "The action game doesn't currently have a release date...",
      "url": "https://kotaku.com/god-of-war-laufey-promises-physical-disc-version-all-but-confirming-2027-launch-2000714778",
      "publishedAt": "2026-07-10T20:29:38Z",
      "processed_at": "2026-07-11T23:56:01.341431+00:00"
    },
    {
      "title": "Ransomware Used Microsoft-Signed Malicious Driver to Kill EDR: 10 Hosts Hit Before Encryption - Tech Times",
      "source": {
        "name": "Tech Times"
      },
      "description": "Ransomware EDR killers just leveled up: GodDamn ransomware used PoisonX — a kernel driver bearing a ...",
      "url": "https://www.techtimes.com/articles/320091/20260710/ransomware-used-microsoft-signed-malicious-driver-kill-edr-10-hosts-hit-before-encryption.htm",
      "publishedAt": "2026-07-10T17:55:43Z",
      "processed_at": "2026-07-11T23:56:01.341431+00:00"
    },
    {
      "title": "EU Can’t Force Sony To Keep Making Physical Games, Says Consumer Rights Commissioner - Kotaku",
      "source": {
        "name": "Kotaku"
      },
      "description": "The European Union won't stop the all-digital future that video game fans are facing...",
      "url": "https://kotaku.com/eu-cant-force-sony-to-keep-making-physical-games-says-consumer-rights-commissioner-2000714728",
      "publishedAt": "2026-07-10T17:31:28Z",
      "processed_at": "2026-07-11T23:56:01.341431+00:00"
    },
    {
      "title": "What Xbox's layoffs, massive reboot says about the gaming industry - KUOW",
      "source": {
        "name": "KUOW News and Information"
      },
      "description": "Microsoft plans to reduce Xbox by 3,200 jobs over the next fiscal year, calling it “the most signifi...",
      "url": "https://www.kuow.org/stories/what-xbox-s-layoffs-massive-reboot-says-about-the-gaming-industry",
      "publishedAt": "2026-07-10T17:29:12Z",
      "processed_at": "2026-07-11T23:56:01.341431+00:00"
    },
    {
      "title": "Google's Pixel 11 Pro Fold Gets Major Approval - Droid Life",
      "source": {
        "name": "Droid Life"
      },
      "description": "A new Google phone just rolled through the FCC today, a device that we believe to be the Pixel 11 Pr...",
      "url": "https://www.droid-life.com/2026/07/10/google-pixel-11-pro-fold-just-landed-at-the-fcc/",
      "publishedAt": "2026-07-10T17:20:53Z",
      "processed_at": "2026-07-11T23:56:01.341431+00:00"
    },
    {
      "title": "\"Just too gay\" - designer Robert Yang is battling censorship to launch a collection of his award-winning games on Steam and Itch, and it's completely free - Eurogamer.net",
      "source": {
        "name": "Eurogamer.net"
      },
      "description": "Yang's \"ongoing re-remaster\" compilation Radiator Forever is launching with four games included, and...",
      "url": "https://www.eurogamer.net/robert-yang-radiator-forever-collection-steam-itch-free",
      "publishedAt": "2026-07-10T16:50:45Z",
      "processed_at": "2026-07-11T23:56:01.341431+00:00"
    },
    {
      "title": "\"We really squeezed the PS5 as much as we could\": Ubisoft talks tech on Assassin's Creed Black Flag Resynced - Digital Foundry",
      "source": {
        "name": "Digitalfoundry.net"
      },
      "description": "How a 13-year-old game becomes a modern graphical showcase....",
      "url": "https://www.digitalfoundry.net/features/we-really-squeezed-the-ps5-as-much-as-we-could-ubisoft-talks-tech-on-assassins-creed-black-flag-resynced",
      "publishedAt": "2026-07-10T16:44:11Z",
      "processed_at": "2026-07-11T23:56:01.341431+00:00"
    },
    {
      "title": "Motorola has the chance to do something special with the Edge 70 Max, so why am I skeptical? - PhoneArena",
      "source": {
        "name": "PhoneArena"
      },
      "description": "",
      "url": "https://www.phonearena.com/news/motorola-edge-70-max-could-be-something-special-but-i-am-skeptical-editorial_id181778",
      "publishedAt": "2026-07-10T16:28:27Z",
      "processed_at": "2026-07-11T23:56:01.341431+00:00"
    },
    {
      "title": "Dumb Co dared me to trade my iPhone for a hacked flip phone - TechCrunch",
      "source": {
        "name": "TechCrunch"
      },
      "description": "Dumb Co sells flip phones that sync to your smartphone, bridging the infinite connectivity of the iP...",
      "url": "https://techcrunch.com/2026/07/10/dumb-co-dared-me-to-trade-my-iphone-for-a-hacked-flip-phone/",
      "publishedAt": "2026-07-10T16:06:49Z",
      "processed_at": "2026-07-11T23:56:01.341431+00:00"
    }
  ],
  "lastUpdated": "2026-07-11T23:56:01.341526+00:00",
  "source": "NewsAPI",
  "metadata": {
    "processed_by": "GitHub Actions",
    "script_version": "2.0.0",
    "compatible_with": "scripts.js NewsManager"
  }
}