{
  "status": "success",
  "totalResults": 10,
  "articles": [
    {
      "title": "No, Target and Walmart are not removing Xbox products from their stores — as Xbox misinformation reaches new levels - Windows Central",
      "source": {
        "name": "Windows Central"
      },
      "description": "One thing after another, Microsoft is forced to respond time and time again to ongoing rumors that i...",
      "url": "https://www.windowscentral.com/gaming/no-target-and-walmart-are-not-removing-xbox-products-from-their-stores-as-xbox-misinformation-reaches-new-levels",
      "publishedAt": "2025-10-13T01:39:00Z",
      "processed_at": "2025-10-14T01:27:50.219976+00:00"
    },
    {
      "title": "Pokémon GO Events This Week (13 October – 19 October 2025) - Pokémon GO Hub",
      "source": {
        "name": "Pokemon GO Hub"
      },
      "description": "Pokémon GO’s October 6 to October 12 schedule brings the spooky season month in the Tales of Transfo...",
      "url": "https://pokemongohub.net/post/event/pokemon-go-events-this-week-13-october-19-october-2025/",
      "publishedAt": "2025-10-13T00:27:04Z",
      "processed_at": "2025-10-14T01:27:50.219976+00:00"
    },
    {
      "title": "‘Real American’ debuts, but that’s not Hulk Hogan walking out, brother - Cageside Seats",
      "source": {
        "name": "Cageside Seats"
      },
      "description": "Hulk Hogan’s iconic WWE entrance theme turns 40 — but it wasn’t originally meant for the Hulkster....",
      "url": "https://www.cagesideseats.com/wwe/389484/hulk-hogan-real-american-entrance-theme-40th-anniversary-wwe",
      "publishedAt": "2025-10-13T00:00:00Z",
      "processed_at": "2025-10-14T01:27:50.219976+00:00"
    },
    {
      "title": "Everything we know about Final Sentence - Dexerto",
      "source": {
        "name": "Dexerto"
      },
      "description": "Final Sentence is swapping trigger fingers for fast APM with its unique spin on the battle royale fo...",
      "url": "https://www.dexerto.com/gaming/everything-we-know-about-final-sentence-3265822/",
      "publishedAt": "2025-10-12T21:22:27Z",
      "processed_at": "2025-10-14T01:27:50.219976+00:00"
    },
    {
      "title": "VALORANT: Everything about Patch 11.08, including weapons, agents, and map changes - Sheep Esports",
      "source": {
        "name": "Sheepesports.com"
      },
      "description": "Explore expert insights and breaking news in League of Legends Esports, brought to you by Sheep Espo...",
      "url": "https://www.sheepesports.com/articles/valorant-everything-about-patch-11-08-including-weapons-agents-and-map-changes/en",
      "publishedAt": "2025-10-12T20:56:30Z",
      "processed_at": "2025-10-14T01:27:50.219976+00:00"
    },
    {
      "title": "What Google Material 3 Expressive redesigns are rolling out [Updated] - 9to5Google",
      "source": {
        "name": "9to5google.com"
      },
      "description": "Material 3 Expressive redesigns are rolling out to Google apps, and here’s our list of what’s availa...",
      "url": "http://9to5google.com/2025/10/12/google-material-3-expressive-redesign/",
      "publishedAt": "2025-10-12T19:45:00Z",
      "processed_at": "2025-10-14T01:27:50.219976+00:00"
    },
    {
      "title": "Battlefield 6 issues \"fix\" for jump momentum bug and is \"monitoring\" Breakthrough player counts - Eurogamer",
      "source": {
        "name": "Eurogamer.net"
      },
      "description": "Battlefield 6 has issued a fix for an issue where jump momentum gets \"unintentionally interrupted\" d...",
      "url": "https://www.eurogamer.net/battlefield-6-issues-fix-for-jump-momentum-bug-and-is-monitoring-breakthrough-player-counts",
      "publishedAt": "2025-10-12T18:47:50Z",
      "processed_at": "2025-10-14T01:27:50.219976+00:00"
    },
    {
      "title": "Time is running out for millions of Windows 10 users, but here's the 1 trick for a free one-year extension - Tom's Guide",
      "source": {
        "name": "Tom's Guide"
      },
      "description": "Put off upgrading to Windows 11 for another 12 months without paying a dime...",
      "url": "https://www.tomsguide.com/computing/windows-operating-systems/time-is-running-out-for-millions-of-windows-10-users-but-heres-the-1-trick-for-a-free-one-year-extension",
      "publishedAt": "2025-10-12T18:46:36Z",
      "processed_at": "2025-10-14T01:27:50.219976+00:00"
    },
    {
      "title": "Stephanie Vaquer just gave Becky Lynch a reason to come after her title - Cageside Seats",
      "source": {
        "name": "Cageside Seats"
      },
      "description": "A friendly glance between Crown Jewel champions is enough to start a storyline between “The Man” and...",
      "url": "https://www.cagesideseats.com/wwe/389375/stephanie-vaquer-just-gave-becky-lynch-a-reason-to-come-after-her-title",
      "publishedAt": "2025-10-12T18:00:00Z",
      "processed_at": "2025-10-14T01:27:50.219976+00:00"
    },
    {
      "title": "Report: Screenshots for Rare’s Everwild Unveiled, Featuring UI and More - MP1st",
      "source": {
        "name": "http://mp1st.com/category/news"
      },
      "description": "MP1st uncovered posthumous details and exclusive screenshots from Rare's cancelled title, Everwild, ...",
      "url": "https://mp1st.com/news/screenshots-rares-everwild-featuring-ui-gameplay-details",
      "publishedAt": "2025-10-12T17:58:46Z",
      "processed_at": "2025-10-14T01:27:50.219976+00:00"
    }
  ],
  "lastUpdated": "2025-10-14T01:27:50.220054+00:00",
  "source": "NewsAPI",
  "metadata": {
    "processed_by": "GitHub Actions",
    "script_version": "2.0.0",
    "compatible_with": "scripts.js NewsManager"
  }
}