{
  "status": "success",
  "totalResults": 8,
  "articles": [
    {
      "title": "Game anywhere with $250 off the Lenovo Legion Go S ahead of Black Friday - Mashable",
      "source": {
        "name": "Mashable"
      },
      "description": "A lengthy battery life and comfy form factor make for great on-the-go sessions, especially over the ...",
      "url": "https://mashable.com/article/early-black-friday-deal-2025-lenovo-legion-go-s",
      "publishedAt": "2025-11-23T23:53:52Z",
      "processed_at": "2025-11-25T03:15:48.364136+00:00"
    },
    {
      "title": "Google denies analyzing your emails for AI training - here's what happened - ZDNET",
      "source": {
        "name": "ZDNet"
      },
      "description": "You can opt out of the features in question if you're still concerned. Here's how....",
      "url": "https://www.zdnet.com/article/google-denies-analyzing-your-emails-for-ai-training-heres-what-happened/",
      "publishedAt": "2025-11-23T23:30:00Z",
      "processed_at": "2025-11-25T03:15:48.364136+00:00"
    },
    {
      "title": "Save Over 20% On Black Myth Wukong at Amazon For Black Friday - IGN",
      "source": {
        "name": "IGN"
      },
      "description": "Save over 20% on Black Myth Wukong and jump into the massive action-RPG for less - just in time for ...",
      "url": "https://www.ign.com/articles/black-myth-wukong-deal-at-amazon-for-black-friday-2025",
      "publishedAt": "2025-11-23T23:28:27Z",
      "processed_at": "2025-11-25T03:15:48.364136+00:00"
    },
    {
      "title": "Metroid Prime 4: Beyond Demo Now Available At Switch 2 Kiosks (US) - Nintendo Life",
      "source": {
        "name": "Nintendo Life"
      },
      "description": "Samus returns this December...",
      "url": "https://www.nintendolife.com/news/2025/11/metroid-prime-4-beyond-demo-now-available-at-switch-2-kiosks-us",
      "publishedAt": "2025-11-23T22:30:00Z",
      "processed_at": "2025-11-25T03:15:48.364136+00:00"
    },
    {
      "title": "These 4-Cylinder Engines Make Power You'd Expect From A V8 - Jalopnik",
      "source": {
        "name": "Jalopnik"
      },
      "description": "The Mercedes-AMG M 139, Mitsubishi 4B11T, and Volvo Twin Engine are four-cylinder engines that can m...",
      "url": "https://www.jalopnik.com/2030364/powerful-four-cylinder-engines/",
      "publishedAt": "2025-11-23T22:25:00Z",
      "processed_at": "2025-11-25T03:15:48.364136+00:00"
    },
    {
      "title": "Elden Ring Is Under $20 Again for Black Friday - IGN",
      "source": {
        "name": "IGN"
      },
      "description": "Save big on trips to the Lands Between with Black Friday discounts on Elden Ring, its Shadow of the ...",
      "url": "https://www.ign.com/articles/elden-ring-is-under-20-again-and-nightreign-has-a-big-discount-too-for-black-friday",
      "publishedAt": "2025-11-23T20:37:35Z",
      "processed_at": "2025-11-25T03:15:48.364136+00:00"
    },
    {
      "title": "Super Mario Odyssey Gets a Big Black Friday Discount With a Free Switch 2 Upgrade - IGN",
      "source": {
        "name": "IGN"
      },
      "description": "Super Mario Odyssey got a 10 out of 10 from IGN, and it's arguably only got even better. It's also n...",
      "url": "https://www.ign.com/articles/super-mario-odyssey-black-friday-deal-2025",
      "publishedAt": "2025-11-23T20:36:58Z",
      "processed_at": "2025-11-25T03:15:48.364136+00:00"
    },
    {
      "title": "Apple iPhone 18 Launch, Price, Features & Specifications Details - Here Is Everything You Need To Know - Wccftech",
      "source": {
        "name": "Wccftech"
      },
      "description": "The iPhone 18 lineup will be significantly different next year so check out our detailed launch, pri...",
      "url": "https://wccftech.com/roundup/apple-iphone-18-launch-price-features-specifications-roundup/",
      "publishedAt": "2025-11-23T20:00:00Z",
      "processed_at": "2025-11-25T03:15:48.364136+00:00"
    }
  ],
  "lastUpdated": "2025-11-25T03:15:48.364198+00:00",
  "source": "NewsAPI",
  "metadata": {
    "processed_by": "GitHub Actions",
    "script_version": "2.0.0",
    "compatible_with": "scripts.js NewsManager"
  }
}